PyplotAnnotation/PyplotAnnotation.py
PyplotAnnotation/__init__.py
PyplotAnnotation-1.1.0.dist-info/LICENSE
PyplotAnnotation-1.1.0.dist-info/METADATA
PyplotAnnotation-1.1.0.dist-info/WHEEL
PyplotAnnotation-1.1.0.dist-info/top_level.txt
PyplotAnnotation-1.1.0.dist-info/RECORD
