Metadata-Version: 2.1
Name: PyplotAnnotation
Version: 1.1.0
Summary: Quickly draw segmentation dataset
Home-page: https://github.com/Rignak/PyplotAnnotation
Author: Aurélien COLIN
Author-email: aureliencolin@hotmail.com
License: UNKNOWN
Platform: UNKNOWN
Classifier: Programming Language :: Python :: 3.6
Classifier: License :: OSI Approved :: GNU General Public License v3 (GPLv3)
Requires-Python: >=3.6
Requires-Dist: matplotlib (>=3.1.1)
Requires-Dist: fire (>=0.2.1)
Requires-Dist: PIL (>=1.1.7)
